asynchuobi/__init__.py
asynchuobi/auth.py
asynchuobi/enums.py
asynchuobi/exceptions.py
asynchuobi/urls.py
asynchuobi/api/__init__.py
asynchuobi/api/schemas.py
asynchuobi/api/clients/__init__.py
asynchuobi/api/clients/account.py
asynchuobi/api/clients/algo.py
asynchuobi/api/clients/generic.py
asynchuobi/api/clients/margin.py
asynchuobi/api/clients/market.py
asynchuobi/api/clients/order.py
asynchuobi/api/clients/subuser.py
asynchuobi/api/clients/wallet.py
asynchuobi/api/request/__init__.py
asynchuobi/api/request/abstract.py
asynchuobi/api/request/strategy.py
asynchuobi/ws/__init__.py
asynchuobi/ws/enums.py
asynchuobi/ws/ws_client.py
asynchuobi/ws/ws_connection.py
asynchuobi-0.0.1.dist-info/LICENSE
asynchuobi-0.0.1.dist-info/METADATA
asynchuobi-0.0.1.dist-info/WHEEL
asynchuobi-0.0.1.dist-info/top_level.txt
asynchuobi-0.0.1.dist-info/RECORD
