Metadata-Version: 2.1
Name: asynchuobi
Version: 0.0.1
Summary: Unofficial asynchronous python client for Huobi cryptoexchange
Home-page: https://github.com/sometastycake/asynchuobi
Author: Mike M
Author-email: stopthisworldplease@outlook.com
License: MIT
Platform: UNKNOWN
Requires-Python: >=3.7
License-File: LICENSE
Requires-Dist: aiohttp (>=3.8.3)
Requires-Dist: pydantic (>=1.10.2)
